mldiag/__init__.py
mldiag/augmentors.py
mldiag/cli.py
mldiag/descriptors.py
mldiag/diagnostics.py
mldiag/methods.py
mldiag/metrics.py
mldiag/report.py
mldiag/runners.py
mldiag/services.py
mldiag/session.py
mldiag/tasks.py
mldiag/wrappers.py
mldiag-0.0.1.data/data/resources/ml-diag.css
mldiag-0.0.1.data/data/resources/ml-diag.jpg
tests/__init__.py
tests/test_wrappers.py
mldiag-0.0.1.dist-info/LICENSE
mldiag-0.0.1.dist-info/METADATA
mldiag-0.0.1.dist-info/WHEEL
mldiag-0.0.1.dist-info/top_level.txt
mldiag-0.0.1.dist-info/RECORD
