Metadata-Version: 2.1
Name: mldiag
Version: 0.0.1
Summary: A framework to diagnose ML models
Home-page: https://github.com/AI-MEN/MLDiag/blob/master/mldiag
Author: Aymen SHABOU
Author-email: aymen.shabou@gmail.com
License: UNKNOWN
Keywords: diagnose,machine learning,deep learning,augmenter,tensorflow,pytorch,scikit-learn
Platform: UNKNOWN
Classifier: Programming Language :: Python :: 3
Classifier: License :: OSI Approved :: MIT License
Classifier: Operating System :: OS Independent
Requires-Python: >=3.7
Requires-Dist: tensorflow-datasets (==3.2.1)
Requires-Dist: fire (==0.3.1)
Requires-Dist: tensorflow (==2.0.0)
Requires-Dist: tensorflow-hub (==0.9.0)
Requires-Dist: nlpaug (==0.0.20)
Requires-Dist: pillow (==7.2.0)
Requires-Dist: plotly (==4.10.0)
Requires-Dist: yattag (==1.13.2)
Requires-Dist: nptyping (==1.3.0)
Requires-Dist: flask (==1.1.2)
Requires-Dist: pyyaml (==5.3.1)
Requires-Dist: pandas (==1.1.2)
Requires-Dist: requests (==2.24.0)
Requires-Dist: protobuf (==3.13.0)
